LICENSE
README.md
setup.cfg
setup.py
pyinspectx/__init__.py
pyinspectx/inspector.py
pyinspectx.egg-info/PKG-INFO
pyinspectx.egg-info/SOURCES.txt
pyinspectx.egg-info/dependency_links.txt
pyinspectx.egg-info/top_level.txt
pyinspectx/visitors/FunctionVisitor.py
pyinspectx/visitors/__init__.py
pyinspectx/visitors/ast_generator.py