Metadata-Version: 2.1
Name: pyinspectx
Version: 0.0.1
Summary: A simple tool to help you debug and see all the final values of the variables in every scope.
Author: Thoosje (Thomas Nelissen)
Author-email: <thoosje2005@gmail.com>
Keywords: python,debugging,debugger,variables,scope,local
Classifier: Development Status :: 3 - Alpha
Classifier: Intended Audience :: Developers
Classifier: Programming Language :: Python :: 3
Classifier: Operating System :: Unix
Classifier: Operating System :: MacOS :: MacOS X
Classifier: Operating System :: Microsoft :: Windows
License-File: LICENSE
